{
	"miniprogramRoot": "miniprogram/",
	"cloudfunctionRoot": "cloudfunctions/",
	"setting": {
		"urlCheck": true,
		"es6": true,
		"enhance": true,
		"postcss": true,
		"preloadBackgroundData": false,
		"minified": true,
		"newFeature": true,
		"coverView": true,
		"nodeModules": true,
		"autoAudits": false,
		"showShadowRootInWxmlPanel": true,
		"scopeDataCheck": false,
		"uglifyFileName": true,
		"checkInvalidKey": true,
		"checkSiteMap": true,
		"uploadWithSourceMap": true,
		"babelSetting": {
			"ignore": [],
			"disablePlugins": [],
			"outputPath": ""
		},
		"bundle": true,
		"useCompilerModule": false,
		"userConfirmedUseCompilerModuleSwitch": false
	},
	"libVersion": "2.7.0",
	"appid": "wx0f4cd6cc7c3d703e",
	"projectname": "%E5%87%A4%E9%B8%A3%E7%8F%AD",
	"simulatorType": "wechat",
	"simulatorPluginLibVersion": {},
	"permissions": {
		"openapi": [
			"subscribeMessage.send"
		]
	},
	"cloudfunctionTemplateRoot": "cloudfunctionTemplate",
	"condition": {
		"search": {
			"current": -1,
			"list": []
		},
		"conversation": {
			"current": -1,
			"list": []
		},
		"plugin": {
			"current": -1,
			"list": []
		},
		"game": {
			"list": []
		},
		"gamePlugin": {
			"current": -1,
			"list": []
		},
		"miniprogram": {
			"current": -1,
			"list": [
				{
					"id": 0,
					"name": "pages/msgPages/msgPages",
					"pathName": "pages/msgPages/msgPages",
					"query": "id=e8b1b114-58b6-4f8a-9a93-faa7ef17d369",
					"scene": null
				}
			]
		}
	}
}